{
  "intents": [
    {
      "tag": "greeting",
      "patterns": [
        "hello", "hi", "hey", "good morning", "good afternoon", "good evening",
        "how are you", "what's up", "hola", "hey there", "hi there", "hello there",
        "sup", "yo", "howdy", "greetings", "heya", "hi bot", "hey bot"
      ],
      "responses": [
        "Hello! How can I assist you today?",
        "Hi! Welcome, how can I help?",
        "Hey! What do you need?"
      ]
    },
    {
      "tag": "goodbye",
      "patterns": [
        "bye", "goodbye", "see you later", "talk to you soon", "farewell", "bye bye",
        "thanks and goodbye", "I'm leaving", "see you", "catch you later", "later",
        "gotta go", "peace out", "adios", "cya", "ttyl", "have a good one"
      ],
      "responses": [
        "Goodbye! Have a great day.",
        "See you later! I'm here if you need me.",
        "Bye! Come back soon."
      ]
    },
    {
      "tag": "thanks",
      "patterns": [
        "thank you", "thanks", "thank you very much", "thanks a lot", "appreciate it",
        "thx", "ty", "thank u", "thanks bro", "gracias", "perfect thanks", "ok thanks"
      ],
      "responses": [
        "You're welcome! Anything else?",
        "My pleasure! Let me know if you need more help.",
        "Glad I could help!"
      ]
    },
    {
      "tag": "return_request",
      "patterns": [
        "i want to return a product", "need to make a return", "how do i return", "return please",
        "can i return this", "i want a refund", "refund please", "i want to send it back",
        "i changed my mind", "not what i expected", "i don't like it"
      ],
      "responses": [
        "I'm sorry to hear that. Could you briefly tell me the reason for the return?",
        "No problem. What's the issue with the product?"
      ]
    },
    {
      "tag": "return_reason_provided",
      "patterns": [
        "damaged", "defective", "broken", "doesn't work", "arrived damaged", "came broken",
        "wrong size", "wrong color", "poor quality", "missing parts", "not working",
        "dead on arrival", "scratched", "cracked", "doesn't fit"
      ],
      "responses": [
        "Got it – the product arrived {0}. We'll start the return process right away. Could you please provide your order number?",
        "Understood, it's {0}. Initiating return/refund. Just need your order number to continue.",
        "Thanks for letting me know ({0}). Return approved. Please share the order number when ready."
      ]
    },
    {
      "tag": "cancel_order",
      "patterns": [
        "cancel my order", "i want to cancel", "how to cancel order", "stop my order",
        "cancel please", "i don't want it anymore", "cancel the purchase", "remove order"
      ],
      "responses": [
        "Sure, I can help you cancel. Please provide your order number.",
        "No problem. Give me the order number and I'll cancel it right away."
      ]
    },
    {
      "tag": "track_order",
      "patterns": [
        "where is my order", "track shipment", "tracking number", "when will it arrive",
        "order status", "my order hasn't arrived", "tracking", "delivery status",
        "where's my package", "when does it get here", "how many days left"
      ],
      "responses": [
        "Sure! To check the status, please provide your order number.",
        "Just give me the order or tracking number and I'll look it up."
      ]
    },
    {
      "tag": "track_order_status",
      "patterns": [],
      "responses": [
        "Order #{} → Shipped! Expected delivery in 2–3 business days.",
        "Order #{} is out for delivery today. Tracking link sent to your email.",
        "Order #{} is in transit (left warehouse yesterday). Estimated arrival: 2 days."
      ]
    },
    {
      "tag": "delivery_time",
      "patterns": [
        "how long does shipping take", "delivery time", "how many days", "when will it be delivered",
        "shipping duration", "express shipping", "standard shipping", "fast delivery"
      ],
      "responses": [
        "Standard shipping takes 3–7 business days. Express option available (1–2 days).",
        "Delivery usually takes 3–5 business days depending on your location."
      ]
    },
    {
      "tag": "payment",
      "patterns": [
        "how do i pay", "payment methods", "can i pay with card", "paypal", "credit card",
        "do you accept paypal", "cash on delivery", "payment options", "how to pay"
      ],
      "responses": [
        "We accept all major credit/debit cards, PayPal, and bank transfer.",
        "You can pay with card or PayPal at checkout."
      ]
    },
    {
      "tag": "warranty",
      "patterns": [
        "does it have warranty", "how long is the warranty", "guarantee", "is it guaranteed",
        "warranty period", "what if it breaks", "return policy warranty"
      ],
      "responses": [
        "All products come with a 12-month warranty against manufacturing defects.",
        "Yes, 1-year warranty included. We'll repair or replace if needed."
      ]
    },
    {
      "tag": "product_info",
      "patterns": [
        "what material is it", "what colors are available", "sizes", "what's it made of",
        "product details", "tell me about this item", "specifications", "features"
      ],
      "responses": [
        "Sure! Which product are you interested in? I can give you all the details.",
        "Let me know the product name or code and I'll tell you everything."
      ]
    },
    {
      "tag": "product_cellphone",
      "patterns": ["cellphone","phone","smartphone","iphone","samsung","mobile"],
      "responses": [
        "About the {}: Available colors → black, silver, blue, gold | Storage: 128/256 GB | Material: aluminum & glass | 108 MP camera | 5G ready. Anything else?",
        "The {} comes in multiple colors and storage options. Battery lasts all day and has fast charging. Need more specs or want to see stock?"
      ]
    },

    {
      "tag": "product_laptop",
      "patterns": ["laptop","macbook","notebook","computer","pc"],
      "responses": [
        "About the {}: 13–16 inch models | Intel i7 / Apple M2 | 16 GB RAM | 512 GB–1 TB SSD | Up to 18 hours battery. Available in silver & space gray. Anything else?",
        "The {} has excellent performance and Retina display (on MacBook). Perfect for work or study. Want to know price or availability?"
      ]
    },

    {
      "tag": "product_clothing",
      "patterns": ["shirt","t-shirt","pants","jeans","hoodie","jacket","dress"],
      "responses": [
        "About the {}: Available sizes S–XXL | Colors: black, white, navy, gray | 100 % cotton | Machine washable. Super comfortable! Need size chart or stock?",
        "The {} comes in various colors and fits true to size. Very good reviews. Anything else I can help with?"
      ]
    },

    {
      "tag": "product_headphones",
      "patterns": ["headphones","earbuds","airpods","earphones","wireless headphones"],
      "responses": [
        "About the {}: Active noise cancellation | 30-hour battery | Wireless charging case | Available in white & black. Sound quality is excellent. Anything else?",
        "The {} have amazing bass and comfort. Perfect for calls and music. Want to check price?"
      ]
    },

    {
      "tag": "product_generic_fallback",
      "patterns": [], 
      "responses": [
        "Thanks for asking about the {}! It's one of our popular items. Available in several colors/sizes. Let me know if you want more details or place an order.",
        "Got it — the {} is in stock. Anything specific you'd like to know (price, colors, shipping… )?"
      ]
    },
    {
      "tag": "size_exchange",
      "patterns": [
        "wrong size", "i need a different size", "can i exchange size", "change to L",
        "too small", "too big", "size exchange", "i ordered wrong size"
      ],
      "responses": [
        "No problem! We can exchange the size. Please provide your order number.",
        "Of course. Tell me the order number and the new size you need."
      ]
    },
    {
      "tag": "order_number",
      "patterns": [
        "my order is", "order number", "it's", "the order is", "tracking",
        "12345", "ABC123", "ORDER-98765", "#55555", "my order # is"
      ],
      "responses": [
        "Perfect! With order #{} I'll process your request right away.",
        "Got it! Order #{} noted. I'll take care of it."
      ]
    },
    {
      "tag": "confirm",
      "patterns": [
        "yes", "ok", "sure", "yes please", "no", "not really", "affirmative", "negative",
        "yep", "nope", "alright"
      ],
      "responses": [
        "Great! Proceeding with the request.",
        "Okay, noted. Anything else I can help with?"
      ]
    },
    {
      "tag": "not_understood",
      "patterns": [],
      "responses": [
        "I'm sorry, I didn't understand. Could you rephrase?",
        "Hmm, not sure what you mean. Can you try saying it differently?",
        "Let's try that again – what can I assist with?"
      ]
    }
  ]
}